odoo10_addon_product_profile_example-10.0.1.0.1.99.dev9-py2.7-nspkg.pth
odoo/addons/product_profile_example/README.rst
odoo/addons/product_profile_example/__init__.py
odoo/addons/product_profile_example/__manifest__.py
odoo/addons/product_profile_example/product.profile.csv
odoo/addons/product_profile_example/product_product_demo.xml
odoo/addons/product_profile_example/profile.py
odoo/addons/product_profile_example/i18n/de.po
odoo/addons/product_profile_example/i18n/es.po
odoo/addons/product_profile_example/i18n/fr.po
odoo/addons/product_profile_example/i18n/hr.po
odoo/addons/product_profile_example/i18n/product_profile_example.pot
odoo/addons/product_profile_example/i18n/sl.po
odoo/addons/product_profile_example/static/description/akretion.png
odoo/addons/product_profile_example/static/description/field.png
odoo/addons/product_profile_example/static/description/icon.png
odoo/addons/product_profile_example/static/description/index.html
odoo/addons/product_profile_example/static/description/list.png
odoo/addons/product_profile_example/tests/__init__.py
odoo/addons/product_profile_example/tests/test_profile.py
odoo10_addon_product_profile_example-10.0.1.0.1.99.dev9.dist-info/METADATA
odoo10_addon_product_profile_example-10.0.1.0.1.99.dev9.dist-info/RECORD
odoo10_addon_product_profile_example-10.0.1.0.1.99.dev9.dist-info/WHEEL
odoo10_addon_product_profile_example-10.0.1.0.1.99.dev9.dist-info/namespace_packages.txt
odoo10_addon_product_profile_example-10.0.1.0.1.99.dev9.dist-info/top_level.txt
