Metadata-Version: 2.1
Name: odoo10-addon-product-profile-example
Version: 10.0.1.0.1.99.dev9
Summary: Product Profile Use Case
Home-page: http://www.akretion.com/
Author: Akretion, Odoo Community Association (OCA)
Author-email: support@odoo-community.org
License: AGPL-3
Platform: UNKNOWN
Classifier: Programming Language :: Python
Classifier: Framework :: Odoo
Classifier: License :: OSI Approved :: GNU Affero General Public License v3
Requires-Python: ~=2.7
Requires-Dist: odoo10-addon-product-profile
Requires-Dist: odoo (<10.1dev,>=10.0)
